rst2gemtext.py
rst2gemtext-0.5.0.dist-info/entry_points.txt
rst2gemtext-0.5.0.dist-info/licenses/COPYING
rst2gemtext-0.5.0.dist-info/WHEEL
rst2gemtext-0.5.0.dist-info/METADATA
rst2gemtext-0.5.0.dist-info/RECORD
