Metadata-Version: 2.4
Name: rst2gemtext
Version: 0.5.0
Summary: Converts reStructuredText to Gemtext (Gemini markup format)
Keywords: restructuredtext,rst,convert,gemtext,gmi,gemini,docutils
Author: Fabien LOISON
Requires-Python: >=3.9
License-Expression: GPL-3.0-or-later
License-File: COPYING
Requires-Dist: docutils
Requires-Dist: pygments
Requires-Dist: nox ; extra == "dev"
Requires-Dist: flit ; extra == "dev"
Requires-Dist: black ; extra == "dev"
Requires-Dist: flake8 ; extra == "dev"
Requires-Dist: flake8-pyproject ; extra == "dev"
Requires-Dist: validate-pyproject ; extra == "dev"
Requires-Dist: pytest ; extra == "dev"
Project-URL: Chat, https://discord.gg/P77sWhuSs4
Project-URL: changelog, https://github.com/flozz/rst2gemtext?tab=readme-ov-file#changelog
Project-URL: documentation, https://github.com/flozz/rst2gemtext/blob/master/README.rst
Project-URL: donate, https://github.com/flozz/rst2gemtext#support-this-project
Project-URL: issues, https://github.com/flozz/rst2gemtext/issues
Project-URL: source, https://github.com/flozz/rst2gemtext
Provides-Extra: dev
